<?xml version="1.0" encoding="UTF-8"?>
<tei:TEI xmlns:tei="http://www.tei-c.org/ns/1.0"
         xmlns:j="http://jewishliturgy.org/ns/jlptei/2"
         xml:lang="he">
  <tei:teiHeader>
    <tei:fileDesc>
      <tei:titleStmt>
        <tei:title type="main" xml:lang="he">אַשְׁרֵי</tei:title>
        <tei:title type="alt" xml:lang="en">Ashrei</tei:title>
        <tei:respStmt>
          <tei:resp key="mrk">Markup editor</tei:resp>
          <tei:name ref="urn:x-opensiddur:contributor:opensiddur.org/example-editor">Example Editor</tei:name>
        </tei:respStmt>
      </tei:titleStmt>
      <tei:publicationStmt>
        <tei:distributor>
          <tei:ref target="http://opensiddur.org">Open Siddur Project</tei:ref>
        </tei:distributor>
        <tei:idno type="urn">urn:x-opensiddur:text:prayer:ashrei@original-example</tei:idno>
        <tei:availability status="free">
          <tei:licence target="http://www.creativecommons.org/publicdomain/zero/1.0/">Creative Commons Zero (Public Domain Dedication)</tei:licence>
        </tei:availability>
      </tei:publicationStmt>
      <tei:sourceDesc>
        <tei:p>See <tei:ref target="urn:x-opensiddur:text:prayer:pesukei_dezimra@original-example">project index for source information</tei:ref></tei:p>
      </tei:sourceDesc>
    </tei:fileDesc>
  </tei:teiHeader>
  <tei:text xml:lang="he">
    <tei:body>
      <tei:div corresp="urn:x-opensiddur:text:prayer:ashrei" n="ashrei">
        <tei:head>אַשְׁרֵי</tei:head>
        <tei:p>
          <tei:milestone unit="verse" n="1" corresp="urn:x-opensiddur:text:prayer:ashrei/1"/>אַשְׁרֵי יוֹשְׁבֵי בֵיתֶךָ עוֹד יְהַלְלוּךָ סֶּלָה.
          <tei:milestone unit="verse" n="2" corresp="urn:x-opensiddur:text:prayer:ashrei/2"/>אַשְׁרֵי הָעָם שֶׁכָּכָה לּוֹ אַשְׁרֵי הָעָם שֶׁיֲהֹוָה אֱלֹהָיו.
        </tei:p>
        <tei:div corresp="urn:x-opensiddur:text:prayer:ashrei/tehila_ledavid" n="tehila_ledavid">
          <tei:head>תְּהִלָּה לְדָוִד</tei:head>
          <tei:p>
            <tei:milestone unit="verse" n="3" corresp="urn:x-opensiddur:text:prayer:ashrei/3"/>אֲרוֹמִמְךָ אֱלוֹהַי הַמֶּלֶךְ וַאֲבָרֲכָה שִׁמְךָ לְעוֹלָם וָעֶד.
            <tei:milestone unit="verse" n="4" corresp="urn:x-opensiddur:text:prayer:ashrei/4"/>בְּכָל יוֹם אֲבָרֲכֶךָּ וַאֲהַלְלָה שִׁמְךָ לְעוֹלָם וָעֶד.
            <tei:milestone unit="verse" n="5" corresp="urn:x-opensiddur:text:prayer:ashrei/5"/>גָּדוֹל יְהוָה וּמְהֻלָּל מְאֹד וְלִגְדֻלָּתוֹ אֵין חֵקֶר.
            <tei:milestone unit="verse" n="6" corresp="urn:x-opensiddur:text:prayer:ashrei/6"/>דּוֹר לְדוֹר יְשַׁבַּח מַעֲשֶׂיךָ וּגְבוּרֹתֶיךָ יַגִּידוּ.
          </tei:p>
          <tei:p>
            <tei:milestone unit="verse" n="7" corresp="urn:x-opensiddur:text:prayer:ashrei/7"/>הֲדַר כְּבוֹד הוֹדֶךָ וְדִבְרֵי נִפְלְאֹתֶיךָ אָשִׂיחָה.
            <tei:milestone unit="verse" n="8" corresp="urn:x-opensiddur:text:prayer:ashrei/8"/>וֶעֱזוּז נוֹרְאֹתֶיךָ יֹאמֵרוּ וּגְדוּלָּתְךָ אֲסַפְּרֶנָּה.
            <tei:milestone unit="verse" n="9" corresp="urn:x-opensiddur:text:prayer:ashrei/9"/>זֵכֶר רַב טוּבְךָ יַבִּיעוּ וְצִדְקָתְךָ יְרַנֵּנוּ.
            <tei:milestone unit="verse" n="10" corresp="urn:x-opensiddur:text:prayer:ashrei/10"/>חַנּוּן וְרַחוּם יְהוָה אֶרֶךְ אַפַּיִם וּגְדָל חָסֶד.
          </tei:p>
          <tei:p>
            <tei:milestone unit="verse" n="11" corresp="urn:x-opensiddur:text:prayer:ashrei/11"/>טוֹב יְהוָה לַכֹּל וְרַחֲמָיו עַל כָּל מַעֲשָׂיו.
            <tei:milestone unit="verse" n="12" corresp="urn:x-opensiddur:text:prayer:ashrei/12"/>יוֹדוּךָ יְהוָה כָּל מַעֲשֶׂיךָ וַחֲסִידֶיךָ יְבָרֲכוּכָה.
            <tei:milestone unit="verse" n="13" corresp="urn:x-opensiddur:text:prayer:ashrei/13"/>כְּבוֹד מַלְכוּתְךָ יֹאמֵרוּ וּגְבוּרָתְךָ יְדַבֵּרוּ.
            <tei:milestone unit="verse" n="14" corresp="urn:x-opensiddur:text:prayer:ashrei/14"/>לְהוֹדִיעַ לִבְנֵי הָאָדָם גְּבוּרֹתָיו וּכְבוֹד הֲדַר מַלְכוּתוֹ.
          </tei:p>
          <tei:p>
            <tei:milestone unit="verse" n="15" corresp="urn:x-opensiddur:text:prayer:ashrei/15"/>מַלְכוּתְךָ מַלְכוּת כָּל עֹלָמִים וּמֶמְשַׁלְתְּךָ בְּכָל דּוֹר וָדֹר.
            <tei:milestone unit="verse" n="16" corresp="urn:x-opensiddur:text:prayer:ashrei/16"/>סוֹמֵךְ יְהוָה לְכָל הַנֹּפְלִים וְזוֹקֵף לְכָל הַכְּפוּפִים.
            <tei:milestone unit="verse" n="17" corresp="urn:x-opensiddur:text:prayer:ashrei/17"/>עֵינֵי כֹל אֵלֶיךָ יְשַׂבֵּרוּ וְאַתָּה נוֹתֵן לָהֶם אֶת אָכְלָם בְּעִתּוֹ.
            <tei:milestone unit="verse" n="18" corresp="urn:x-opensiddur:text:prayer:ashrei/18"/>פּוֹתֵחַ אֶת יָדֶךָ וּמַשְׂבִּיעַ לְכָל חַי רָצוֹן.
          </tei:p>
          <tei:p>
            <tei:milestone unit="verse" n="19" corresp="urn:x-opensiddur:text:prayer:ashrei/19"/>צַדִּיק יְהוָה בְּכָל דְּרָכָיו וְחָסִיד בְּכָל מַעֲשָׂיו.
            <tei:milestone unit="verse" n="20" corresp="urn:x-opensiddur:text:prayer:ashrei/20"/>קָרוֹב יְהוָה לְכָל קֹרְאָיו לְכֹל אֲשֶׁר יִקְרָאֻהוּ בֶאֱמֶת.
            <tei:milestone unit="verse" n="21" corresp="urn:x-opensiddur:text:prayer:ashrei/21"/>רְצוֹן יְרֵאָיו יַעֲשֶׂה וְאֶת שַׁוְעָתָם יִשְׁמַע וְיוֹשִׁיעֵם.
            <tei:milestone unit="verse" n="22" corresp="urn:x-opensiddur:text:prayer:ashrei/22"/>שׁוֹמֵר יְהוָה אֶת כָּל אֹהֲבָיו וְאֵת כָּל הָרְשָׁעִים יַשְׁמִיד.
            <tei:milestone unit="verse" n="23" corresp="urn:x-opensiddur:text:prayer:ashrei/23"/>תְּהִלַּת יְהוָה יְדַבֶּר פִּי וִיבָרֵךְ כָּל בָּשָׂר שֵׁם קָדְשׁוֹ לְעוֹלָם וָעֶד.
          </tei:p>
        </tei:div>
      </tei:div>
    </tei:body>
  </tei:text>
</tei:TEI>
